pipeline/__init__.py
pipeline/pipeline.py
pipeline/test.py
pipeline/drug/__init__.py
pipeline/drug/allinone.py
pipeline/drug/analysis.py
pipeline/drug/count.py
pipeline/drug/featureCounts.py
pipeline/drug/mapping.py
pipeline/drug/trim.py
pipeline/templates/css/bootstrap.min.css
pipeline/templates/css/buttons.dataTables.min.css
pipeline/templates/css/dataTables.jqueryui.min.css
pipeline/templates/css/jquery-ui-git.css
pipeline/templates/css/jquery-ui.css
pipeline/templates/css/jquery.dataTables.css
pipeline/templates/html/common/barcode_summary.html
pipeline/templates/html/common/logo.html
pipeline/templates/html/common/trim_summary.html
pipeline/templates/html/drug/base.html
pipeline/templates/html/drug/featureCounts_summary.html
pipeline/templates/html/drug/mapping_summary.html
pipeline/templates/image/logo.jpeg
pipeline/templates/js/bootstrap.min.js
pipeline/templates/js/buttons.flash.min.js
pipeline/templates/js/buttons.html5.min.js
pipeline/templates/js/buttons.print.min.js
pipeline/templates/js/dataTables.buttons.min.js
pipeline/templates/js/dataTables.jqueryui.min.js
pipeline/templates/js/jquery.dataTables.js
pipeline/templates/js/jquery.dataTables.min.js
pipeline/templates/js/jquery.min.3.3.1.js
pipeline/templates/js/jquery.min.js
pipeline/templates/js/jszip.min.js
pipeline/templates/js/plotly-1.58.4.min.js
pipeline/templates/js/plotly-latest.min.js
pipeline/toolkits/__init__.py
pipeline/toolkits/analysis.R
pipeline/toolkits/barcode.py
pipeline/toolkits/parallel.py
pipeline/toolkits/report.py
pipeline/toolkits/step.py
pipeline/toolkits/tools.R
pipeline/toolkits/utils.py
DRUGseq_tools-0.0.1.dist-info/METADATA
DRUGseq_tools-0.0.1.dist-info/WHEEL
DRUGseq_tools-0.0.1.dist-info/entry_points.txt
DRUGseq_tools-0.0.1.dist-info/top_level.txt
DRUGseq_tools-0.0.1.dist-info/RECORD
