Metadata-Version: 2.1
Name: DRUGseq-tools
Version: 0.0.1
Summary: Transcriptome Analysis Pipeline for DRUG-seq
Home-page: https://github.com/zzzseeu/pipeline
Author: zhouxin
Author-email: xinzhou@xremed.com
Classifier: Programming Language :: Python :: 3
Classifier: License :: OSI Approved :: MIT License
Classifier: Operating System :: OS Independent
Requires-Python: >=3.6
Requires-Dist: cutadapt (==1.18)
Requires-Dist: numpy (==1.21.6)
Requires-Dist: pandas (==1.3.5)
Requires-Dist: jinja2 (==3.1.2)
Requires-Dist: pysam (==0.20.0)
Requires-Dist: scanpy (==1.9.3)
Requires-Dist: scikit-learn (==1.0.2)
Requires-Dist: scipy (==1.7.3)
